strblackout/__init__.py
strblackout/__main__.py
strblackout/blackout.py
strblackout-0.1.1.dist-info/LICENSE
strblackout-0.1.1.dist-info/METADATA
strblackout-0.1.1.dist-info/WHEEL
strblackout-0.1.1.dist-info/entry_points.txt
strblackout-0.1.1.dist-info/top_level.txt
strblackout-0.1.1.dist-info/RECORD
