Metadata-Version: 2.1
Name: strblackout
Version: 0.1.1
Summary: Blackout the string (str)
Home-page: https://github.com/jojoee/strblackout
Author: Nathachai Thongniran
Author-email: inid3a@gmail.com
License: MIT
Platform: UNKNOWN
Classifier: License :: OSI Approved :: MIT License
Classifier: Programming Language :: Python :: 3
Classifier: Programming Language :: Python :: 3.7
License-File: LICENSE
